pywhy_graphs/__init__.py
pywhy_graphs/_version.py
pywhy_graphs/algorithms/__init__.py
pywhy_graphs/algorithms/cyclic.py
pywhy_graphs/algorithms/generic.py
pywhy_graphs/algorithms/multidomain.py
pywhy_graphs/algorithms/pag.py
pywhy_graphs/algorithms/tests/test_cyclic.py
pywhy_graphs/algorithms/tests/test_generic.py
pywhy_graphs/algorithms/tests/test_multidomain_algs.py
pywhy_graphs/algorithms/tests/test_pag.py
pywhy_graphs/array/__init__.py
pywhy_graphs/array/api.py
pywhy_graphs/array/tests/test_api.py
pywhy_graphs/classes/__init__.py
pywhy_graphs/classes/admg.py
pywhy_graphs/classes/augmented.py
pywhy_graphs/classes/base.py
pywhy_graphs/classes/cpdag.py
pywhy_graphs/classes/functions.py
pywhy_graphs/classes/networkxprotocol.py
pywhy_graphs/classes/pag.py
pywhy_graphs/classes/tests/test_graph.py
pywhy_graphs/classes/timeseries/__init__.py
pywhy_graphs/classes/timeseries/base.py
pywhy_graphs/classes/timeseries/conversion.py
pywhy_graphs/classes/timeseries/cpdag.py
pywhy_graphs/classes/timeseries/digraph.py
pywhy_graphs/classes/timeseries/functions.py
pywhy_graphs/classes/timeseries/graph.py
pywhy_graphs/classes/timeseries/mixededge.py
pywhy_graphs/classes/timeseries/pag.py
pywhy_graphs/classes/timeseries/tests/test_basic_timeseries.py
pywhy_graphs/classes/timeseries/tests/test_equivalence_classes.py
pywhy_graphs/classes/timeseries/tests/test_functions.py
pywhy_graphs/classes/timeseries/tests/test_mixededge_stationary_timeseries.py
pywhy_graphs/classes/timeseries/tests/test_mixededge_timeseries.py
pywhy_graphs/classes/timeseries/tests/test_networkx.py
pywhy_graphs/config.py
pywhy_graphs/export/__init__.py
pywhy_graphs/export/ananke.py
pywhy_graphs/export/causallearn.py
pywhy_graphs/export/numpy.py
pywhy_graphs/export/pcalg.py
pywhy_graphs/export/tests/test_ananke.py
pywhy_graphs/export/tests/test_causal_learn.py
pywhy_graphs/export/tests/test_numpy.py
pywhy_graphs/export/tests/test_pag_tetrad.txt
pywhy_graphs/export/tests/test_pcalg.py
pywhy_graphs-0.1.0.dist-info/LICENSE
pywhy_graphs-0.1.0.dist-info/METADATA
pywhy_graphs-0.1.0.dist-info/WHEEL
pywhy_graphs-0.1.0.dist-info/RECORD
