Metadata-Version: 2.1
Name: pywhy-graphs
Version: 0.1.0
Summary: Causal Graphs for Python
Home-page: https://github.com/py-why/pywhy-graphs
License: MIT
Keywords: causality,graphs,causal-inference,graphical-model
Author: PyWhy Community
Author-email: adam.li@columbia.edu
Requires-Python: >=3.8,<3.12
Classifier: Development Status :: 4 - Beta
Classifier: License :: OSI Approved :: MIT License
Classifier: Programming Language :: Python :: 3
Classifier: Programming Language :: Python :: 3.8
Classifier: Programming Language :: Python :: 3.9
Classifier: Programming Language :: Python :: 3.10
Classifier: Programming Language :: Python :: 3.11
Provides-Extra: viz
Requires-Dist: importlib-resources ; python_version < "3.10"
Requires-Dist: networkx (>=3.1,<4.0)
Requires-Dist: numpy (>=1.21.0,<2.0.0)
Requires-Dist: pygraphviz ; extra == "viz"
Requires-Dist: scipy (>=1.8.0,<2.0.0)
Project-URL: Documentation, https://py-why.github.io/pywhy-graphs
Project-URL: Repository, https://github.com/py-why/pywhy-graphs
